{"cameraMode":{"drawMode":0,"name":"Shaded","section":"Shading Mode"},"sceneLighting":true,"audioPlay":false,"sceneViewState":{"m_AlwaysRefresh":false,"showFog":true,"showSkybox":true,"showFlares":true,"showImageEffects":true,"showParticleSystems":true,"showVisualEffectGraphs":true,"m_FxEnabled":true},"in2DMode":false,"pivot":{"x":6.305734157562256,"y":1.7305512428283692,"z":5.943425178527832},"rotation":{"x":0.63490229845047,"y":0.06581224501132965,"z":-0.054416473954916,"w":0.7678590416908264},"size":0.4744330644607544,"orthographic":false}